<?xml version="1.0" encoding="utf-8"?>
<XnaContent xmlns:ns="Microsoft.Xna.Framework">
  <Asset Type="GameXML.SpriteMap">
    <TextureList>
      <Item>
        <Name>npcFemale3SmokingRight1</Name>
        <X>0</X>
        <Y>97</Y>
        <Width>96</Width>
        <Height>96</Height>
      </Item>
      <Item>
        <Name>npcFemale3SmokingRight2</Name>
        <X>194</X>
        <Y>97</Y>
        <Width>96</Width>
        <Height>96</Height>
      </Item>
      <Item>
        <Name>npcFemale3SmokingRight3</Name>
        <X>97</X>
        <Y>0</Y>
        <Width>96</Width>
        <Height>96</Height>
      </Item>
      <Item>
        <Name>npcFemale3SmokingRight4</Name>
        <X>97</X>
        <Y>97</Y>
        <Width>96</Width>
        <Height>96</Height>
      </Item>
      <Item>
        <Name>npcFemale3SmokingRight5</Name>
        <X>0</X>
        <Y>194</Y>
        <Width>96</Width>
        <Height>96</Height>
      </Item>
      <Item>
        <Name>npcFemale3SmokingRight6</Name>
        <X>97</X>
        <Y>194</Y>
        <Width>96</Width>
        <Height>96</Height>
      </Item>
      <Item>
        <Name>npcFemale3SmokingRight7</Name>
        <X>194</X>
        <Y>0</Y>
        <Width>96</Width>
        <Height>96</Height>
      </Item>
      <Item>
        <Name>npcFemale3SmokingRight8</Name>
        <X>0</X>
        <Y>0</Y>
        <Width>96</Width>
        <Height>96</Height>
      </Item>
      <Item>
        <Name>npcFemale3SmokingRight9</Name>
        <X>194</X>
        <Y>194</Y>
        <Width>96</Width>
        <Height>96</Height>
      </Item>
      <Item>
        <Name>npcFemale3SmokingRight10</Name>
        <X>0</X>
        <Y>291</Y>
        <Width>96</Width>
        <Height>96</Height>
      </Item>
      <Item>
        <Name>npcFemale3SmokingRight11</Name>
        <X>97</X>
        <Y>291</Y>
        <Width>96</Width>
        <Height>96</Height>
      </Item>
      <Item>
        <Name>npcFemale3SmokingRight12</Name>
        <X>194</X>
        <Y>291</Y>
        <Width>96</Width>
        <Height>96</Height>
      </Item>
      <Item>
        <Name>npcFemale3SmokingRight13</Name>
        <X>291</X>
        <Y>0</Y>
        <Width>96</Width>
        <Height>96</Height>
      </Item>
      <Item>
        <Name>npcFemale3SmokingRight14</Name>
        <X>291</X>
        <Y>97</Y>
        <Width>96</Width>
        <Height>96</Height>
      </Item>
    </TextureList>
  </Asset>
</XnaContent>